{
  "product": "FCUBS",
  "module": "Inventory Management",
  "document_count": 1,
  "documents": [
    {
      "name": "Instruments Inventory Tracking User Guide-FCUBS",
      "filename": "Instruments Inventory Tracking User Guide-FCUBS.pdf",
      "index_file": "Instruments Inventory Tracking User Guide-FCUBS.json",
      "total_pages": 62,
      "total_sections": 80,
      "toc_method": "builtin",
      "top_sections": [
        "Contents",
        "1. Preface",
        "1.1 Introduction",
        "1.2 Audience",
        "1.3 Documentation Accessibility",
        "1.4 Abbreviations",
        "1.5 Organization",
        "1.6 Related Documents",
        "1.7 Glossary of Icons",
        "2. Overview - Instruments Inventory Tracking",
        "2.1 Instruments Inventory Tracking",
        "2.2 Scope of the Module",
        "2.3 IV Module Functions & Features",
        "3. Maintenances",
        "3.1 Bank Parameters Maintenance"
      ],
      "summary": "This document is a user guide for Instruments Inventory Tracking in Oracle FLEXCUBE Universal Banking version 14.7.0.0.0, published in November 2022. This page contains contact information and legal disclaimers for Oracle Financial Services Software Limited's Instruments Inventory Tracking User Guid",
      "keywords": [
        "abbreviations",
        "accessibility",
        "adjust",
        "adjusting",
        "alerts",
        "allowed",
        "analysis",
        "annexure",
        "audience",
        "automatic",
        "balance",
        "bank",
        "banker",
        "batch",
        "book",
        "branch",
        "branches",
        "bulk",
        "casa",
        "catalog",
        "cheque",
        "code",
        "comprehensive",
        "confirm",
        "contents",
        "defining",
        "definition",
        "demand",
        "denomination",
        "details",
        "documentation",
        "documents",
        "down",
        "draft",
        "drill",
        "eod",
        "examples",
        "excess",
        "extensive",
        "external",
        "features",
        "flexible",
        "flow",
        "function",
        "functions",
        "gateway",
        "gateways",
        "generic",
        "glossary",
        "hand",
        "icons",
        "illustration",
        "inputs",
        "inquiries",
        "inquiry",
        "instruments",
        "interface",
        "interfaces",
        "introduction",
        "inventory",
        "issue",
        "issuer",
        "issuing",
        "level",
        "maintenance",
        "maintenances",
        "mandatory",
        "master",
        "module",
        "operations",
        "order",
        "ordering",
        "organization",
        "outputs",
        "overview",
        "parameters",
        "passbook",
        "pattern",
        "preface",
        "process",
        "processing",
        "program",
        "receipts",
        "receive",
        "receiving",
        "related",
        "request",
        "requesting",
        "scope",
        "screen",
        "services",
        "specifying",
        "stock",
        "stockflow",
        "stocks",
        "summary",
        "teller",
        "tracking",
        "transaction",
        "transactions",
        "traveller",
        "usage",
        "validation",
        "vendor",
        "web",
        "workflow"
      ]
    }
  ]
}